[
  {
    "uid": "EXAMPLE_CHANNEL_MULTI_ITEM_JSON_TTS_1",
    "updateDate": "2019-03-24T00:00:01.0Z",
    "titleText": "The most popular item on ssense today for men is",
    "mainText": "Amelie is the most beautiful girl on earth",
    "redirectionUrl": "https://www.ssense.com"
   },
  {
    "uid": "EXAMPLE_CHANNEL_MULTI_ITEM_JSON_TTS_2",
    "updateDate": "2019-03-24T00:00:00.0Z",
    "titleText": "The most popular item on ssense for women today is",
    "mainText": "Tonight bambi and raccoon are gonna go to the gym and then do a demenegaement",
    "redirectionUrl": "https://www.ssense.com"
  }
]
